url_strip/__init__.py
url_strip/_result.py
url_strip/_special_cases.py
url_strip/_strip.py
url_strip/_types.py
url_strip/testing.py
url_strip-0.2.1.dist-info/LICENSE
url_strip-0.2.1.dist-info/METADATA
url_strip-0.2.1.dist-info/WHEEL
url_strip-0.2.1.dist-info/top_level.txt
url_strip-0.2.1.dist-info/RECORD
