Metadata-Version: 2.1
Name: url-strip
Version: 0.2.1
Summary: Library to strip http urls of tracking elements, and use shorthand variants of urls
Author: ultrabear
Author-email: bearodark@gmail.com
Classifier: Programming Language :: Python :: 3.8
Classifier: Programming Language :: Python :: 3.9
Classifier: Programming Language :: Python :: 3.10
Classifier: Programming Language :: Python :: 3 :: Only
Classifier: Development Status :: 4 - Beta
Classifier: Intended Audience :: Developers
Classifier: Natural Language :: English
Classifier: Operating System :: OS Independent
Classifier: Topic :: Text Processing :: Filters
Classifier: Typing :: Typed
Classifier: License :: OSI Approved :: GNU General Public License v3 (GPLv3)
Requires-Python: >=3.8.0
License-File: LICENSE
Requires-Dist: typing-extensions (<5,>=3.10.0.0)
Provides-Extra: dev
Requires-Dist: mypy ; extra == 'dev'
Requires-Dist: pylint ; extra == 'dev'
Requires-Dist: yapf ; extra == 'dev'
Requires-Dist: toml ; extra == 'dev'
Requires-Dist: pyflakes ; extra == 'dev'
Requires-Dist: pyright ; extra == 'dev'
